<?xml version="1.0" encoding="utf-8" ?>
<dwsync>
<file name="twentyfifteen-rtl.css" server="manpreetk.sgedu.site/www/" local="131178578832939146" remote="131177487000000000" Dst="0" />
<file name="twentyfifteen.css" server="manpreetk.sgedu.site/www/" local="131178578835439050" remote="131177487000000000" Dst="0" />
<file name="twentyfifteen.php" server="manpreetk.sgedu.site/www/" local="131178578842782518" remote="131177487000000000" Dst="0" />
<file name="twentyfourteen-rtl.css" server="manpreetk.sgedu.site/www/" local="131178578847313594" remote="131177487000000000" Dst="0" />
<file name="twentyfourteen.css" server="manpreetk.sgedu.site/www/" local="131178578847626082" remote="131177487000000000" Dst="0" />
<file name="twentyfourteen.php" server="manpreetk.sgedu.site/www/" local="131178578854500818" remote="131177487000000000" Dst="0" />
<file name="twentysixteen-rtl.css" server="manpreetk.sgedu.site/www/" local="131178578859969358" remote="131177487000000000" Dst="0" />
<file name="twentysixteen.css" server="manpreetk.sgedu.site/www/" local="131178578859969358" remote="131177487000000000" Dst="0" />
<file name="twentysixteen.php" server="manpreetk.sgedu.site/www/" local="131178578864656678" remote="131177487000000000" Dst="0" />
</dwsync>