<?xml version="1.0" encoding="utf-8" ?>
<dwsync>
<file name="blank.css" server="manpreetk.sgedu.site/www/" local="131178577502521486" remote="131177487000000000" Dst="0" />
<file name="codemirror-rtl.css" server="manpreetk.sgedu.site/www/" local="131178577507833782" remote="131177487000000000" Dst="0" />
<file name="codemirror.css" server="manpreetk.sgedu.site/www/" local="131178577512364858" remote="131177487000000000" Dst="0" />
<file name="codemirror-rtl.min.css" server="manpreetk.sgedu.site/www/" local="131178577514708518" remote="131177487000000000" Dst="0" />
<file name="codemirror.min.css" server="manpreetk.sgedu.site/www/" local="131178577519552082" remote="131177487000000000" Dst="0" />
<file name="css-editor-rtl.css" server="manpreetk.sgedu.site/www/" local="131178577524083158" remote="131177487000000000" Dst="0" />
<file name="css-editor-rtl.min.css" server="manpreetk.sgedu.site/www/" local="131178577526583062" remote="131177487000000000" Dst="0" />
<file name="css-editor.css" server="manpreetk.sgedu.site/www/" local="131178577530957894" remote="131177487000000000" Dst="0" />
<file name="css-editor.min.css" server="manpreetk.sgedu.site/www/" local="131178577535332726" remote="131177487000000000" Dst="0" />
<file name="use-codemirror-rtl.css" server="manpreetk.sgedu.site/www/" local="131178577542207462" remote="131177487000000000" Dst="0" />
<file name="use-codemirror-rtl.min.css" server="manpreetk.sgedu.site/www/" local="131178577546582294" remote="131177487000000000" Dst="0" />
<file name="use-codemirror.css" server="manpreetk.sgedu.site/www/" local="131178577549082198" remote="131177487000000000" Dst="0" />
<file name="use-codemirror.min.css" server="manpreetk.sgedu.site/www/" local="131178577553457030" remote="131177487000000000" Dst="0" />
</dwsync>